{"timestamp":"2025-01-12T01:08:16.811374574Z","version":"0.1.0","generated_at":"2025-01-12T01:08:16.811374574Z","ci":{"name":"Container Verification Pipeline","team":"CVP Development Team","doc":"https://docs.engineering.redhat.com/display/CVP/Container+Verification+Pipeline+E2E+Documentation","url":"https://jenkins1-cvp.apps.agogos.x13g.p1.openshiftapps.com/job/cvp-brew-operator-bundle-image-trigger/3702/","email":"cvp-ops@redhat.com"},"run":{"url":"https://jenkins-cvp-617017858ebd9a62aec7c3b8.apps.agogos.x13g.p1.openshiftapps.com/job/cvp-redhat-operator-bundle-image-validation-test/17/","log":"https://jenkins-cvp-617017858ebd9a62aec7c3b8.apps.agogos.x13g.p1.openshiftapps.com/job/cvp-redhat-operator-bundle-image-validation-test/17/console","result_files":[]},"artifact":{"type":"cvp","id":"3464739","component":"cvp-redhatopenshiftai","issuer":"exd-cpaas-bot-prod","brew_build_target":"rhods-1.18-rhel-8-containers-candidate","brew_build_tag":"rhods-1.18-rhel-8-container-candidate","nvr":"odh-operator-bundle-container-v1.18.0-587","full_name":"Undefined Artifact Image Full Name","registry_url":"Undefined Artifact Image Registry URL","namespace":"Undefined Artifact Image Namespace","name":"Undefined Artifact Image Name","image_tag":"Undefined Artifact Image Tag","advisory_id":"N/A","scratch":"false"},"pipeline":{"name":"cvp-redhat-operator-bundle-image-validation-test","id":"af7fe370-9383-4fb6-b0fc-75931fc6189b","status":"complete","build":"17","cpaas_pipeline_id":"f647ee37-1d2d-48c1-9fa5-d50aad68275f","runtime":"3518.3","index_image":{"v4.18":"registry-proxy.engineering.redhat.com/rh-osbs/iib:894538","v4.17":"registry-proxy.engineering.redhat.com/rh-osbs/iib:894539","v4.15":"registry-proxy.engineering.redhat.com/rh-osbs/iib:894536","v4.16":"registry-proxy.engineering.redhat.com/rh-osbs/iib:894537","v4.19":"registry-proxy.engineering.redhat.com/rh-osbs/iib:894540","v4.14":"registry-proxy.engineering.redhat.com/rh-osbs/iib:894535"}}}